odoo/addons/l10n_fr_siret_lookup/README.rst
odoo/addons/l10n_fr_siret_lookup/__init__.py
odoo/addons/l10n_fr_siret_lookup/__manifest__.py
odoo/addons/l10n_fr_siret_lookup/i18n/fr.po
odoo/addons/l10n_fr_siret_lookup/i18n/l10n_fr_siret_lookup.pot
odoo/addons/l10n_fr_siret_lookup/models/__init__.py
odoo/addons/l10n_fr_siret_lookup/models/res_partner.py
odoo/addons/l10n_fr_siret_lookup/readme/CONTRIBUTORS.rst
odoo/addons/l10n_fr_siret_lookup/readme/CREDITS.rst
odoo/addons/l10n_fr_siret_lookup/readme/DESCRIPTION.rst
odoo/addons/l10n_fr_siret_lookup/readme/USAGE.rst
odoo/addons/l10n_fr_siret_lookup/security/ir.model.access.csv
odoo/addons/l10n_fr_siret_lookup/static/description/icon.png
odoo/addons/l10n_fr_siret_lookup/static/description/index.html
odoo/addons/l10n_fr_siret_lookup/views/res_partner.xml
odoo/addons/l10n_fr_siret_lookup/wizard/__init__.py
odoo/addons/l10n_fr_siret_lookup/wizard/fr_siret_lookup.py
odoo/addons/l10n_fr_siret_lookup/wizard/fr_siret_lookup_view.xml
odoo14_addon_l10n_fr_siret_lookup-14.0.1.1.0.dist-info/METADATA
odoo14_addon_l10n_fr_siret_lookup-14.0.1.1.0.dist-info/WHEEL
odoo14_addon_l10n_fr_siret_lookup-14.0.1.1.0.dist-info/top_level.txt
odoo14_addon_l10n_fr_siret_lookup-14.0.1.1.0.dist-info/RECORD
